subject_researcher_mcp/__init__.py
subject_researcher_mcp/research_engine.py
subject_researcher_mcp/server.py
subject_researcher_mcp-0.2.0.dist-info/METADATA
subject_researcher_mcp-0.2.0.dist-info/WHEEL
subject_researcher_mcp-0.2.0.dist-info/entry_points.txt
subject_researcher_mcp-0.2.0.dist-info/licenses/LICENSE
subject_researcher_mcp-0.2.0.dist-info/RECORD
