Metadata-Version: 2.4
Name: subject-researcher-mcp
Version: 0.2.0
Summary: Enhanced Subject Researcher MCP - Iterative target-driven research with multi-vertical search, quality metrics, and sophisticated claim mining
Project-URL: Homepage, https://github.com/your-org/subject-researcher-mcp
Project-URL: Documentation, https://github.com/your-org/subject-researcher-mcp/wiki
Project-URL: Repository, https://github.com/your-org/subject-researcher-mcp.git
Project-URL: Issues, https://github.com/your-org/subject-researcher-mcp/issues
Author-email: Enhanced Subject Researcher Team <research-support@your-org.com>
License: MIT
License-File: LICENSE
Keywords: ai,claim-mining,credibility-scoring,evidence-based,iterative-research,mcp,multi-vertical-search,quality-metrics,research,web-search
Classifier: Development Status :: 5 - Production/Stable
Classifier: Intended Audience :: Developers
Classifier: Intended Audience :: Science/Research
Classifier: License :: OSI Approved :: MIT License
Classifier: Operating System :: OS Independent
Classifier: Programming Language :: Python :: 3
Classifier: Programming Language :: Python :: 3.10
Classifier: Programming Language :: Python :: 3.11
Classifier: Programming Language :: Python :: 3.12
Classifier: Topic :: Internet :: WWW/HTTP :: Indexing/Search
Classifier: Topic :: Scientific/Engineering :: Information Analysis
Classifier: Topic :: Software Development :: Libraries :: Python Modules
Requires-Python: >=3.10
Requires-Dist: beautifulsoup4>=4.12.0
Requires-Dist: duckduckgo-search>=8.0.0
Requires-Dist: httpx>=0.24.0
Requires-Dist: lxml>=4.9.0
Requires-Dist: mcp>=0.4.0
Requires-Dist: wikipedia-api>=0.8.0
Provides-Extra: ai
Requires-Dist: google-generativeai>=0.3.0; extra == 'ai'
Provides-Extra: dev
Requires-Dist: bandit>=1.7.0; extra == 'dev'
Requires-Dist: build>=0.10.0; extra == 'dev'
Requires-Dist: mypy>=1.0.0; extra == 'dev'
Requires-Dist: pytest-asyncio>=0.21.0; extra == 'dev'
Requires-Dist: pytest-cov>=4.0.0; extra == 'dev'
Requires-Dist: pytest-mock>=3.10.0; extra == 'dev'
Requires-Dist: pytest>=7.0.0; extra == 'dev'
Requires-Dist: ruff>=0.1.0; extra == 'dev'
Requires-Dist: safety>=2.3.0; extra == 'dev'
Requires-Dist: twine>=4.0.0; extra == 'dev'
Provides-Extra: performance
Requires-Dist: aiofiles>=23.0.0; extra == 'performance'
Requires-Dist: uvloop>=0.17.0; extra == 'performance'
